wing/__init__.py
wing/cv.py
wing/model_eval.py
wing/pd.py
wing/pd_utils.py
wing/plot.py
wing/plot_utils.py
wing/preprocess.py
wing/split.py
wing/tree.py
wing-0.0.6.dist-info/METADATA
wing-0.0.6.dist-info/WHEEL
wing-0.0.6.dist-info/top_level.txt
wing-0.0.6.dist-info/RECORD
