Metadata-Version: 2.1
Name: wing
Version: 0.0.6
Summary: Utility functions for data science
Home-page: https://github.com/puzzler10/wing
Author: Tom Roth
Author-email: tom.roth@live.com.au
License: UNKNOWN
Platform: UNKNOWN
Classifier: Programming Language :: Python :: 3
Classifier: License :: OSI Approved :: MIT License
Classifier: Operating System :: OS Independent
Requires-Dist: numpy
Requires-Dist: pandas
Requires-Dist: seaborn
Requires-Dist: sklearn
Requires-Dist: scipy
Provides-Extra: pdpbox
Requires-Dist: pdpbox ; extra == 'pdpbox'
